stringflow/__init__.py
stringflow/main.py
stringflow/strings.py
stringflow/utils.py
stringflow-0.0.2.dist-info/METADATA
stringflow-0.0.2.dist-info/WHEEL
stringflow-0.0.2.dist-info/top_level.txt
stringflow-0.0.2.dist-info/RECORD
